{"data":{"site":{"siteMetadata":{"title":"2019 Habit Tracker","author":"Josh Garrisi"}},"markdownRemark":{"id":"5a6bbd06-5df2-52f7-a85d-9d4a6fd4dba0","excerpt":"Kids finally went back to school today. I learned how to edit this git repo from my iPad Pro so i don’t have to do this only on my work MacBook. Hoping to meet…","html":"<p>Kids finally went back to school today.</p>\n<p>I learned how to edit this git repo from my iPad Pro so i don’t have to do this only on my work MacBook.</p>\n<p>Hoping to meet with Gaylin this evening to discuss putting a wall in to create a study.</p>","frontmatter":{"title":"New skills","date":"January 08, 2019"}}},"pageContext":{"slug":"/2019-01-08/","previous":{"fields":{"slug":"/2019-01-05/"},"frontmatter":{"title":"Pretty good Saturday"}},"next":null}}